mirumoji/__init__.py
mirumoji/gui_launcher.py
mirumoji/launcher.py
mirumoji/gui/__init__.py
mirumoji/gui/core.py
mirumoji/gui/main.py
mirumoji/gui/models.py
mirumoji/gui/paths.py
mirumoji/gui/router.py
mirumoji/gui/web/favicon.ico
mirumoji/gui/web/index.html
mirumoji/gui/web/main.js
mirumoji-2.6.0.dist-info/licenses/LICENSE
mirumoji-2.6.0.dist-info/METADATA
mirumoji-2.6.0.dist-info/WHEEL
mirumoji-2.6.0.dist-info/entry_points.txt
mirumoji-2.6.0.dist-info/top_level.txt
mirumoji-2.6.0.dist-info/RECORD
