Metadata-Version: 2.4
Name: mirumoji
Version: 2.6.0
Summary: CLI and GUI launcher for the Mirumoji project, an open-source, self-hostable Japanese language immersion tool.
Author-email: svdc <svdc1mail@gmail.com>
Maintainer-email: svdc <svdc1mail@gmail.com>
License-Expression: MIT
Project-URL: Homepage, https://github.com/svdC1/mirumoji
Project-URL: Issues, https://github.com/svdC1/mirumoji/issues
Keywords: japanese,video-player,language,cli,gui,language-learning
Classifier: Programming Language :: Python :: 3
Classifier: Operating System :: OS Independent
Requires-Python: >=3.9
License-File: LICENSE
Requires-Dist: click
Requires-Dist: python-dotenv
Requires-Dist: fastapi
Requires-Dist: uvicorn
Requires-Dist: python-socketio
Requires-Dist: flaskwebgui
Dynamic: license-file
